envelope/__init__.py
envelope/__main__.py
envelope/_auth.py
envelope/address.py
envelope/attachment.py
envelope/constants.py
envelope/envelope.py
envelope/message.py
envelope/parser.py
envelope/smtp_handler.py
envelope/utils.py
envelope-2.2.1.dist-info/LICENSE
envelope-2.2.1.dist-info/METADATA
envelope-2.2.1.dist-info/WHEEL
envelope-2.2.1.dist-info/entry_points.txt
envelope-2.2.1.dist-info/RECORD
