Metadata-Version: 2.3
Name: envelope
Version: 2.2.1
Summary: Insert a message and attachments and send e-mail / sign / encrypt contents by a single line.
License: LGPL-3.0-or-later
Author: Edvard Rejthar
Author-email: edvard.rejthar@nic.cz
Requires-Python: >=3.10
Classifier: License :: OSI Approved :: GNU Lesser General Public License v3 or later (LGPLv3+)
Classifier: Programming Language :: Python :: 3
Classifier: Programming Language :: Python :: 3.10
Classifier: Programming Language :: Python :: 3.11
Classifier: Programming Language :: Python :: 3.12
Classifier: Programming Language :: Python :: 3.13
Requires-Dist: jsonpickle
Requires-Dist: py3-validate-email
Requires-Dist: python-gnupg (>=0.5)
Requires-Dist: python-magic
Project-URL: Homepage, https://github.com/CZ-NIC/envelope
